LICENSE
MANIFEST.in
README.md
setup.py
pyvt/__init__.py
pyvt/_version.py
pyvt.egg-info/PKG-INFO
pyvt.egg-info/SOURCES.txt
pyvt.egg-info/dependency_links.txt
pyvt.egg-info/not-zip-safe
pyvt.egg-info/requires.txt
pyvt.egg-info/top_level.txt