Metadata-Version: 1.1
Name: pyvt
Version: 0.1a4
Summary: Python VirusTotal Private API 2.0 Implementation.
Home-page: https://github.com/anoroozian/pyvt
Author: Arman Noroozian
Author-email: arman.noroozian.developer@gmail.com
License: MIT
Keywords: virustotal api private
Platform: UNKNOWN
Classifier: Development Status :: 3 - Alpha
Classifier: Intended Audience :: Developers
Classifier: Topic :: Software Development :: Libraries :: Python Modules
Classifier: Topic :: Security
Classifier: License :: OSI Approved :: MIT License
Classifier: Operating System :: OS Independent
Classifier: Programming Language :: Python
Classifier: Programming Language :: Python :: 3
